text_cleaner/__init__.py
text_cleaner/main.py
text_cleaner/metadata.py
text_cleaner/processor/__init__.py
text_cleaner/processor/chinese.py
text_cleaner/processor/common.py
text_cleaner/processor/misc.py
text_cleaner/processor/processor.py
text_cleaner-0.2.6.dist-info/DESCRIPTION.rst
text_cleaner-0.2.6.dist-info/METADATA
text_cleaner-0.2.6.dist-info/RECORD
text_cleaner-0.2.6.dist-info/WHEEL
text_cleaner-0.2.6.dist-info/metadata.json
text_cleaner-0.2.6.dist-info/top_level.txt
